LICENSE.txt
README.txt
setup.py
seopy/__init__.py
seopy.egg-info/PKG-INFO
seopy.egg-info/SOURCES.txt
seopy.egg-info/dependency_links.txt
seopy.egg-info/requires.txt
seopy.egg-info/top_level.txt