Metadata-Version: 2.1
Name: seopy
Version: 1.1
Summary: Instantly analyze your SEO issues
Home-page: https://github.com/dhirajberi/seopy
Author: Dhiraj Beri
Author-email: dhirajberi.official@gmail.com
License: MIT
Download-URL: https://github.com/dhirajberi/seopy/archive/refs/tags/1.1.tar.gz
Keywords: seo,seopy
Platform: UNKNOWN
Classifier: Development Status :: 3 - Alpha
Classifier: Intended Audience :: Developers
Classifier: Topic :: Software Development :: Build Tools
Classifier: License :: OSI Approved :: MIT License
Classifier: Programming Language :: Python :: 3
Classifier: Programming Language :: Python :: 3.4
Classifier: Programming Language :: Python :: 3.5
Classifier: Programming Language :: Python :: 3.6
Classifier: Programming Language :: Python :: 3.7
Classifier: Programming Language :: Python :: 3.8
